strudel.utils-0.6.2.dist-info/DESCRIPTION.rst
strudel.utils-0.6.2.dist-info/LICENSE.txt
strudel.utils-0.6.2.dist-info/METADATA
strudel.utils-0.6.2.dist-info/RECORD
strudel.utils-0.6.2.dist-info/WHEEL
strudel.utils-0.6.2.dist-info/metadata.json
strudel.utils-0.6.2.dist-info/top_level.txt
stutils/__init__.py
stutils/decorators.py
stutils/email_utils.py
stutils/mapreduce.py
stutils/sysutils.py
stutils/versions.py
