Metadata-Version: 2.0
Name: strudel.utils
Version: 0.6.2
Summary: Various utils used internally by strudel.* packages
Home-page: https://github.com/cmustrudel/strudel.utils
Author: Marat (@cmu.edu)
Author-email: UNKNOWN
License: GPL v3
Platform: Linux
Platform: Solaris
Platform: Mac OS-X
Platform: Unix
Platform: Windows
Classifier: Development Status :: 4 - Beta
Classifier: Intended Audience :: Science/Research
Classifier: Programming Language :: Python :: 2.7
Classifier: Programming Language :: Python :: 3.4
Classifier: Programming Language :: Python :: 3.5
Classifier: Programming Language :: Python :: 3.6
Classifier: Programming Language :: Python :: 3.7
Classifier: License :: OSI Approved :: GNU General Public License v3 (GPLv3)
Classifier: Operating System :: POSIX :: Linux
Classifier: Topic :: Scientific/Engineering
Requires-Python: >2.6, !=3.0.*, !=3.1.*, !=3.2.*, !=3.3.*, <4
Requires-Dist: ijson
Requires-Dist: numpy
Requires-Dist: pandas (>=0.23)
Requires-Dist: six
